pandas_nlp/__init__.py
pandas_nlp/cache.py
pandas_nlp/model_manager.py
pandas_nlp/models/__init__.py
pandas_nlp/models/fasttext_language_model.py
pandas_nlp/models/language_model.py
pandas_nlp/models/sentence_model.py
pandas_nlp/models/spacy_model.py
pandas_nlp/models/vector_model.py
pandas_nlp/series_accessor.py
pandas_nlp-0.6.0.dist-info/LICENSE
pandas_nlp-0.6.0.dist-info/WHEEL
pandas_nlp-0.6.0.dist-info/METADATA
pandas_nlp-0.6.0.dist-info/RECORD
