Metadata-Version: 2.1
Name: pandas-nlp
Version: 0.6.0
Summary: Pandas extension with NLP functionalities
Home-page: https://github.com/jaume-ferrarons/pandas-nlp
License: MIT
Keywords: pandas,nlp,spacy,fasttext
Author: Jaume Ferrarons
Author-email: jaume.ferrarons@gmail.com
Requires-Python: >=3.8,<4.0
Classifier: License :: OSI Approved :: MIT License
Classifier: Programming Language :: Python :: 3
Classifier: Programming Language :: Python :: 3.10
Classifier: Programming Language :: Python :: 3.8
Classifier: Programming Language :: Python :: 3.9
Requires-Dist: appdirs (>=1.4.4,<2.0.0)
Requires-Dist: fasttext (>=0.9.2,<0.10.0)
Requires-Dist: numpy (>=1.15.0)
Requires-Dist: pandas (>=1.3.0,<2.0.0)
Requires-Dist: requests (>=2.28.1,<3.0.0)
Requires-Dist: spacy (>=3.0.0,<4.0.0)
Project-URL: Repository, https://github.com/jaume-ferrarons/pandas-nlp
